{
  "folder": "L5NrzwAEG7JeY4vN",
  "name": "Formulae: Vampire Oil",
  "type": "diagrams",
  "_id": "hxf0MmoCkglXbzcB",
  "img": "https://assets.forge-vtt.com/bazaar/core/icons/sundries/documents/blueprint-recipe-alchemical.webp",
  "system": {
    "description": "<p>+5 damage against Vampires.</p>\n<p>&nbsp;</p>\n<p>Requires: 1 Dog Tallow</p>",
    "quantity": "1",
    "weight": 0.1,
    "cost": null,
    "isHidden": false,
    "type": "oil",
    "level": "witcher",
    "isFormulae": true,
    "craftingDC": 0,
    "alchemyDC": 16,
    "craftingTime": "15 Minutes",
    "craftingComponents": [
      {
        "id": "first",
        "quantity": 0,
        "name": ""
      }
    ],
    "investment": 0,
    "learned": false,
    "alchemyComponents": {
      "vitriol": 0,
      "rebis": 0,
      "aether": 1,
      "quebrith": 0,
      "hydragenum": 0,
      "vermilion": 0,
      "sol": 2,
      "caelum": 0,
      "fulgur": 1
    },
    "associatedItemUuid": "Compendium.wtrpg-complete-compendium.gear.Item.K6AeGewUlgGhMsfV",
    "sourcebook": "Corebook",
    "isStored": false,
    "isCarried": true
  },
  "effects": [],
  "sort": 0,
  "ownership": {
    "default": 0,
    "JEflPFTBB5wpYRms": 3,
    "dxC9PYhanWf4xPZG": 3
  },
  "flags": {
    "scene-packer": {
      "hash": "7eb236081931b69e15490bdee0718099aec82d1e"
    }
  },
  "_stats": {
    "compendiumSource": null,
    "duplicateSource": null,
    "coreVersion": "13.347",
    "systemId": "TheWitcherTRPG",
    "systemVersion": "v12.20.0",
    "exportSource": null
  },
  "_key": "!items!hxf0MmoCkglXbzcB"
}
