{
  "name": "Phoenix Feathers",
  "type": "component",
  "img": "https://assets.forge-vtt.com/bazaar/systems/TheWitcherTRPG/assets/assets/images/fulgur.png",
  "system": {
    "description": "",
    "quantity": 1,
    "weight": 0.1,
    "cost": 176,
    "isHidden": false,
    "associatedDiagram": {},
    "type": "substances",
    "rarity": "Rare",
    "location": "Phoenixes",
    "quantityObtainable": "N/A",
    "forage": "N/A",
    "substanceType": "fulgur",
    "sourcebook": "A Witcher's Journal"
  },
  "effects": [],
  "folder": "Oy18pSm2SrAbOh22",
  "flags": {
    "cf": {
      "id": "temp_jmpyik2v7b",
      "color": "#ff0000"
    },
    "core": {},
    "scene-packer": {
      "hash": "30fa2c3682004582c88872a837112034c72ee608"
    }
  },
  "_stats": {
    "systemId": "TheWitcherTRPG",
    "systemVersion": "v12.20.0",
    "coreVersion": "13.347",
    "compendiumSource": null,
    "duplicateSource": null,
    "exportSource": null
  },
  "_id": "tyPHH1oTQRl9PEnE",
  "sort": 700000,
  "ownership": {
    "default": 0,
    "dxC9PYhanWf4xPZG": 3
  },
  "_key": "!items!tyPHH1oTQRl9PEnE"
}
