{
  "folder": "TczKQfugrDCiebda",
  "name": "Codi Bywyd",
  "type": "spell",
  "_id": "KEUuBB5joghRG8th",
  "img": "https://assets.forge-vtt.com/652dd4eea9ac2daadb46a415/modules/wtrpg-complete-compendium/packs/images/Magic/Symbol_Earth.png",
  "system": {
    "class": "Spells",
    "level": "novice",
    "source": "earth",
    "domain": "",
    "stamina": "2",
    "staminaIsVar": false,
    "effect": "Codi Bywyd can grow a small plant from seed to maturity in one turn. This allows you to grow herbs and alchemical plants, but not larger plants such as trees.",
    "range": "4m",
    "duration": "Immediate",
    "defence": "None",
    "components": "",
    "alternateComponents": "",
    "preparationTime": "",
    "dificultyCheck": "",
    "danger": "",
    "liftRequirement": "",
    "sideEffect": "",
    "createTemplate": false,
    "templateSize": "",
    "templateType": "",
    "causeDamages": false,
    "damage": "",
    "effects": [
      {
        "id": "first",
        "name": "effect"
      }
    ],
    "defenseOptions": [],
    "regionProperties": {
      "behaviours": {
        "tokenEnter": "",
        "tokenTurnStart": "",
        "tokenPreMove": "",
        "tokenExit": ""
      }
    }
  },
  "effects": [],
  "sort": 500000,
  "ownership": {
    "default": 0,
    "dxC9PYhanWf4xPZG": 3
  },
  "flags": {
    "scene-packer": {
      "hash": "1094bc63390297886a21106b928881654c41e360"
    }
  },
  "_stats": {
    "systemId": "TheWitcherTRPG",
    "systemVersion": "v12.20.0",
    "coreVersion": "13.347",
    "compendiumSource": null,
    "duplicateSource": null,
    "exportSource": null
  },
  "_key": "!items!KEUuBB5joghRG8th"
}
