{
  "folder": "2whTxabRTjq1xj1F",
  "name": "Aurora's Breath",
  "type": "spell",
  "_id": "iV3nHQJhPWLRoUgZ",
  "img": "https://assets.forge-vtt.com/652dd4eea9ac2daadb46a415/modules/wtrpg-complete-compendium/packs/images/Magic/Symbol_Water.png",
  "system": {
    "class": "Spells",
    "level": "novice",
    "source": "Water",
    "domain": "",
    "stamina": 5,
    "staminaIsVar": false,
    "effect": "Developed by the famed Water-Mage, Aurora Henson, to explore submerged ruins off the coast of the Continent, Aurora’s Breath allows you to breath water as well as air through skillful manipulation of water magic.",
    "range": "Self",
    "duration": "30 Minutes",
    "defence": "None",
    "sideEffect": "",
    "createTemplate": false,
    "templateSize": 0,
    "templateType": "",
    "causeDamages": false,
    "damage": "",
    "defenseOptions": [],
    "regionProperties": {
      "behaviours": {
        "tokenEnter": null,
        "tokenTurnStart": null,
        "tokenExit": null,
        "tokenMoveWithin": null
      },
      "createRegionFromTemplate": false
    },
    "damageProperties": {
      "effects": {
        "2yo1de5qDsxgku2Y": {
          "name": "effect",
          "statusEffect": null,
          "percentage": 0,
          "varEffect": false
        }
      },
      "armorPiercing": false,
      "improvedArmorPiercing": false,
      "ablating": false,
      "crushingForce": false,
      "damageIsAblation": false,
      "damageToAllLocations": false,
      "bypassesWornArmor": false,
      "bypassesNaturalArmor": false,
      "defenseDifferenceMultiplier": false,
      "defenseMultiplierCap": 5,
      "variableDamage": false,
      "oilEffect": "",
      "silverTrait": false,
      "silverDamage": "",
      "isMeteorite": false,
      "isNonLethal": false
    },
    "description": "",
    "quantity": "1",
    "weight": 0,
    "cost": 0,
    "sourcebook": "",
    "isHidden": false,
    "isStored": false,
    "isCarried": true,
    "damageType": "elemental",
    "createsShield": false,
    "shield": "",
    "doesHeal": false,
    "heal": "",
    "selfEffects": [],
    "onCastEffects": [],
    "attackOptions": [
      "spell"
    ],
    "spellAttackSkill": "spellcasting",
    "applyMeleeBonus": false,
    "applyRangedMeleeBonus": false,
    "isThrowable": false,
    "defenseProperties": {
      "parrying": false,
      "defendsAgainst": [],
      "modifier": 0
    }
  },
  "effects": [
    {
      "name": "Aurora's Breath",
      "origin": "Compendium.wtrpg-complete-compendium.magic.Item.iV3nHQJhPWLRoUgZ",
      "duration": {
        "rounds": null,
        "startTime": null,
        "seconds": null,
        "combat": null,
        "turns": null,
        "startRound": null,
        "startTurn": null
      },
      "disabled": false,
      "img": "https://assets.forge-vtt.com/652dd4eea9ac2daadb46a415/modules/wtrpg-complete-compendium/packs/images/Magic/Symbol_Water.png",
      "_id": "PZv3Bi4RhsaHpH7R",
      "type": "base",
      "system": {
        "applySelf": true,
        "applyOnTarget": false,
        "applyOnHit": false,
        "applyOnDamage": false
      },
      "changes": [],
      "description": "<p>Developed by the famed Water-Mage, Aurora Henson, to explore submerged ruins off the coast of the Continent, Aurora’s Breath allows you to breath water as well as air through skillful manipulation of water magic.</p>",
      "tint": "#ffffff",
      "transfer": false,
      "statuses": [],
      "sort": 0,
      "flags": {},
      "_stats": {
        "compendiumSource": null,
        "duplicateSource": null,
        "coreVersion": "13.347",
        "systemId": "TheWitcherTRPG",
        "systemVersion": "v12.10.1",
        "exportSource": null
      },
      "_key": "!items.effects!iV3nHQJhPWLRoUgZ.PZv3Bi4RhsaHpH7R"
    }
  ],
  "sort": 0,
  "ownership": {
    "default": 0
  },
  "flags": {
    "scene-packer": {
      "hash": "9a85fb482c29e39f542b648022493a7c7a0914d4"
    }
  },
  "_stats": {
    "systemId": "TheWitcherTRPG",
    "systemVersion": "v13.14.0",
    "coreVersion": "13.351",
    "compendiumSource": null,
    "duplicateSource": null,
    "exportSource": null
  },
  "_key": "!items!iV3nHQJhPWLRoUgZ"
}
