{
  "folder": "pXX2M1DrueYRdMbN",
  "name": "Cavalry Trousers",
  "type": "armor",
  "_id": "OhrBeeRj1lbWuo6W",
  "img": "https://assets.forge-vtt.com/bazaar/core/icons/equipment/leg/pants-copper-fabric-pants.webp",
  "system": {
    "description": "‘Less they’re a dragoon your average cavalryman’s probably not gonna wear a ton of armor. These dark trouser are only reinforced by leather straps.",
    "quantity": "1",
    "weight": 0.5,
    "cost": 75,
    "isHidden": false,
    "reliability": 0,
    "reliabilityMax": 0,
    "headStopping": 0,
    "headMaxStopping": 0,
    "torsoStopping": 0,
    "torsoMaxStopping": 0,
    "leftArmStopping": 0,
    "leftArmMaxStopping": 0,
    "rightArmStopping": 0,
    "rightArmMaxStopping": 0,
    "leftLegStopping": 3,
    "leftLegMaxStopping": 3,
    "rightLegStopping": 3,
    "rightLegMaxStopping": 3,
    "type": "Light",
    "avail": "Common",
    "enhancements": 0,
    "effects": [],
    "encumb": 0,
    "location": "Leg",
    "bludgeoning": false,
    "slashing": false,
    "piercing": false,
    "enhancementItemIds": [],
    "isStored": false,
    "equipped": false,
    "sourcebook": "Corebook",
    "associatedDiagramUuid": "Compendium.wtrpg-complete-compendium.crafting.Item.GlQGI1cgXlgJY8ac"
  },
  "effects": [],
  "sort": -100000,
  "ownership": {
    "default": 0,
    "dxC9PYhanWf4xPZG": 3
  },
  "flags": {
    "scene-packer": {
      "hash": "c9a03f8eea801959088fb941da0f2c4382542de1"
    }
  },
  "_stats": {
    "systemId": "TheWitcherTRPG",
    "systemVersion": "v12.20.0",
    "coreVersion": "13.347",
    "compendiumSource": null,
    "duplicateSource": null,
    "exportSource": null
  },
  "_key": "!items!OhrBeeRj1lbWuo6W"
}
