{
  "folder": "dNEWmbHLX50kbh79",
  "name": "De Claudine's Substitution",
  "type": "spell",
  "_id": "AQ5TqqdbPEaq4kt3",
  "img": "https://assets.forge-vtt.com/652dd4eea9ac2daadb46a415/modules/wtrpg-complete-compendium/packs/images/Magic/Symbol_Mixed.png",
  "system": {
    "class": "Spells",
    "level": "journeyman",
    "source": "mixedElements",
    "domain": "",
    "stamina": 8,
    "staminaIsVar": false,
    "effect": "Popular with Alchemists and useful when looking for rare substances in a region, De Claudine’s Substitution allows you to permanently change the Alchemical Substance of one Unit of an Alchemy ingredient to a different Alchemical Substance. \nOnly one Unit of any such transmuted Alchemical Substance can be used in an Alchemical Formula without ruining the concoction.",
    "range": "2m",
    "duration": "Permanent",
    "defence": "None",
    "sideEffect": "",
    "createTemplate": false,
    "templateSize": 0,
    "templateType": "",
    "causeDamages": false,
    "damage": "",
    "defenseOptions": [],
    "regionProperties": {
      "behaviours": {
        "tokenEnter": null,
        "tokenTurnStart": null,
        "tokenExit": null,
        "tokenMoveWithin": null
      },
      "createRegionFromTemplate": false
    },
    "damageProperties": {
      "effects": {
        "CzimTELNvvCEMqtR": {
          "name": "effect",
          "statusEffect": null,
          "percentage": 0,
          "varEffect": false
        }
      },
      "armorPiercing": false,
      "improvedArmorPiercing": false,
      "ablating": false,
      "crushingForce": false,
      "damageIsAblation": false,
      "damageToAllLocations": false,
      "bypassesWornArmor": false,
      "bypassesNaturalArmor": false,
      "defenseDifferenceMultiplier": false,
      "defenseMultiplierCap": 5,
      "variableDamage": false,
      "oilEffect": "",
      "silverTrait": false,
      "silverDamage": "",
      "isMeteorite": false,
      "isNonLethal": false
    },
    "description": "",
    "quantity": "1",
    "weight": 0,
    "cost": 0,
    "sourcebook": "",
    "isHidden": false,
    "isStored": false,
    "isCarried": true,
    "damageType": "elemental",
    "createsShield": false,
    "shield": "",
    "doesHeal": false,
    "heal": "",
    "selfEffects": [],
    "onCastEffects": [],
    "attackOptions": [
      "spell"
    ],
    "spellAttackSkill": "spellcasting",
    "applyMeleeBonus": false,
    "applyRangedMeleeBonus": false,
    "isThrowable": false,
    "defenseProperties": {
      "parrying": false,
      "defendsAgainst": [],
      "modifier": 0
    }
  },
  "effects": [],
  "flags": {
    "scene-packer": {
      "hash": "338536f9aa29f5a57d78a9725c3e34684fb78770"
    }
  },
  "_stats": {
    "compendiumSource": null,
    "duplicateSource": null,
    "exportSource": null,
    "coreVersion": "13.351",
    "systemId": "TheWitcherTRPG",
    "systemVersion": "v13.14.0"
  },
  "ownership": {
    "default": 0,
    "C5Vr3CkGFqAIGkSl": 3
  },
  "sort": 0,
  "_key": "!items!AQ5TqqdbPEaq4kt3"
}
