{
  "folder": "CtVhMF5pHO6lp3qb",
  "name": "Freshen Air",
  "type": "spell",
  "_id": "oXZzdeaxZM78x7cI",
  "img": "https://assets.forge-vtt.com/652dd4eea9ac2daadb46a415/modules/wtrpg-complete-compendium/packs/images/Magic/Symbol_Air.png",
  "system": {
    "class": "Spells",
    "level": "novice",
    "source": "air",
    "domain": "",
    "stamina": "2",
    "staminaIsVar": false,
    "effect": "Freshen Air allows you to clear a 4m radius area (centered around you) of any smoke, poison, or any other tainted air for the duration of the spell.",
    "range": "4m Radius",
    "duration": "Active (2 STA)",
    "defence": "None",
    "components": "",
    "alternateComponents": "",
    "preparationTime": "",
    "dificultyCheck": "",
    "danger": "",
    "liftRequirement": "",
    "sideEffect": "",
    "createTemplate": true,
    "templateSize": "4",
    "templateType": "circle",
    "causeDamages": false,
    "damage": "",
    "effects": [
      {
        "id": "first",
        "name": "effect"
      }
    ],
    "visualEffectDuration": null,
    "defenseOptions": [],
    "regionProperties": {
      "behaviours": {
        "tokenEnter": "",
        "tokenTurnStart": "",
        "tokenPreMove": "",
        "tokenExit": ""
      }
    }
  },
  "effects": [],
  "sort": 0,
  "ownership": {
    "default": 0,
    "dxC9PYhanWf4xPZG": 3
  },
  "flags": {
    "scene-packer": {
      "hash": "110971abdbcf31a320993690f9cc7831a99e297f"
    }
  },
  "_stats": {
    "systemId": "TheWitcherTRPG",
    "systemVersion": "v12.20.0",
    "coreVersion": "13.347",
    "compendiumSource": null,
    "duplicateSource": null,
    "exportSource": null
  },
  "_key": "!items!oXZzdeaxZM78x7cI"
}
