{
  "folder": "vl473v4mC3471KoW",
  "name": "Tent, Large",
  "type": "valuable",
  "_id": "8dABLe8VWPh4G1yJ",
  "img": "https://assets.forge-vtt.com/bazaar/core/icons/environment/settlement/tent-flag.webp",
  "system": {
    "description": "\"This tent's large enough to hold eight people in comfort. Really more designed for merchants to sell goods out of.\"\n-Rodolf Kazmer",
    "quantity": 1,
    "weight": 8,
    "cost": 36,
    "isHidden": false,
    "associatedDiagram": {},
    "type": "general",
    "avail": "Common",
    "effect": "",
    "conceal": "L",
    "quality": "",
    "clickableImage": false,
    "sourcebook": "Corebook"
  },
  "effects": [],
  "sort": 100196,
  "ownership": {
    "default": 0,
    "dxC9PYhanWf4xPZG": 3
  },
  "flags": {
    "scene-packer": {
      "hash": "576ea39be9247165dab86ff6cc669e727dd63cf4"
    }
  },
  "_stats": {
    "systemId": "TheWitcherTRPG",
    "systemVersion": "v1.2.0",
    "coreVersion": "13.347",
    "compendiumSource": null,
    "duplicateSource": null,
    "exportSource": null
  },
  "_key": "!items!8dABLe8VWPh4G1yJ"
}
