{
  "folder": "vl473v4mC3471KoW",
  "name": "Waterskin",
  "type": "valuable",
  "_id": "PAh5z3NNcpJEKEm1",
  "img": "https://assets.forge-vtt.com/bazaar/core/icons/sundries/survival/wetskin-leather-purple.webp",
  "system": {
    "description": "\"Don't tend to run across much fresh water on the road and ya don't wanna be downin' ale all day when you're traveling along a war-front. Keep a waterskin handy and you'll never be thirsty. Heh, or drunk on the field!\"\n-Rodolf Kazmer",
    "quantity": 1,
    "weight": 1,
    "cost": 8,
    "isHidden": false,
    "associatedDiagram": {},
    "type": "general",
    "avail": "Everywhere",
    "effect": "",
    "conceal": "S",
    "quality": "",
    "clickableImage": false,
    "sourcebook": "Corebook"
  },
  "effects": [],
  "sort": 100013,
  "ownership": {
    "default": 0,
    "dxC9PYhanWf4xPZG": 3
  },
  "flags": {
    "scene-packer": {
      "hash": "9cc657740d25effc20194d01c773e627555df36d"
    }
  },
  "_stats": {
    "systemId": "TheWitcherTRPG",
    "systemVersion": "v1.2.0",
    "coreVersion": "13.347",
    "compendiumSource": null,
    "duplicateSource": null,
    "exportSource": null
  },
  "_key": "!items!PAh5z3NNcpJEKEm1"
}
